<?xml version="1.0" encoding="UTF-8"?>
<RegistroFacturaRectificativaNoVerifactu xmlns="https://noverifactu.local/esquema/rectificativa">
  <Cabecera>
    <TipoRegistro>RECTIFICATIVA</TipoRegistro>
    <NIFEmisor>71902382N</NIFEmisor>
    <NIFReceptor>76875187X</NIFReceptor>
    <VersionSIF>1.0.0</VersionSIF>
  </Cabecera>
  <DatosFacturaRectificativa>
    <NumeroFacturaRectificativa>3-R1</NumeroFacturaRectificativa>
    <FechaHoraExpedicion>2026-02-24T14:22:00.000Z</FechaHoraExpedicion>
    <TipoRectificacion>DIFERENCIAS</TipoRectificacion>
    <ImporteTotalRectificativa>60.5</ImporteTotalRectificativa>
  </DatosFacturaRectificativa>
  <ReferenciaFacturaOriginal>
    <NumeroFacturaOriginal>3</NumeroFacturaOriginal>
    <FechaHoraExpedicionOriginal>2026-02-24T14:21:00.000Z</FechaHoraExpedicionOriginal>
    <HashRegistroFacturaOriginal>a51a88a66a6676e562c2b6ef5a485c9e0a660d3006cd9c5aa7b4739da7df4db0</HashRegistroFacturaOriginal>
  </ReferenciaFacturaOriginal>
  <DesgloseFiscal>
    <Impuestos>
      <Impuesto>
        <BaseImponible>50</BaseImponible>
        <TipoImpositivo>21</TipoImpositivo>
        <Cuota>10.5</Cuota>
        <Tipo>IVA</Tipo>
      </Impuesto>
    </Impuestos>
  </DesgloseFiscal>
  <Trazabilidad>
    <NumRegistroAnterior>5</NumRegistroAnterior>
    <NumRegistroActual>6</NumRegistroActual>
    <HashRegistroAnterior>a51a88a66a6676e562c2b6ef5a485c9e0a660d3006cd9c5aa7b4739da7df4db0</HashRegistroAnterior>
    <HashRegistroPropio>fbc46633fb2e279bd5b24fb163df576ed8fce90bb208a8ffedea10d771bbcae1</HashRegistroPropio>
    <IdentificacionSIF>
      <IdSoftware>NOVERIFACTU-DEV-1.0.0</IdSoftware>
      <NIFDesarrollador>71902382N</NIFDesarrollador>
      <fechaDeclaracionResponsable>2026-01-22T11:33:32.000Z</fechaDeclaracionResponsable>
    </IdentificacionSIF>
  </Trazabilidad>
</RegistroFacturaRectificativaNoVerifactu>